RunningTrainsPlot/__init__.py
RunningTrainsPlot/column_flow/__init__.py
RunningTrainsPlot/cyclic_diagram/__init__.py
RunningTrainsPlot/examples/__init__.py
RunningTrainsPlot/passenger_flow/__init__.py
RunningTrainsPlot/speed_curve/__init__.py
RunningTrainsPlot/stock_channel/__init__.py
RunningTrainsPlot/track_occupation/__init__.py
RunningTrainsPlot/utils/__init__.py
railwaytrainsvisualization-2024.1.3.dist-info/METADATA
railwaytrainsvisualization-2024.1.3.dist-info/WHEEL
railwaytrainsvisualization-2024.1.3.dist-info/top_level.txt
railwaytrainsvisualization-2024.1.3.dist-info/RECORD
