Metadata-Version: 2.4
Name: RailwayTrainsVisualization
Version: 2024.1.3
Summary: 为研究人员与工程技术人员提供的可扩展、可交互的铁路可视化工具
Home-page: https://github.com/yourusername/RailwayTrainsVisualization
Author: ZeyuShen
Author-email: sc22zs2@leeds.ac.uk
Classifier: Programming Language :: Python :: 3
Classifier: License :: OSI Approved :: MIT License
Classifier: Operating System :: OS Independent
Requires-Python: >=3.6
Requires-Dist: numpy>=1.20.0
Requires-Dist: pandas>=1.0.0
Requires-Dist: matplotlib>=3.3.0
Requires-Dist: plotly>=5.0.0
Dynamic: author
Dynamic: author-email
Dynamic: classifier
Dynamic: description
Dynamic: description-content-type
Dynamic: home-page
Dynamic: requires-dist
Dynamic: requires-python
Dynamic: summary
